odoo8_addon_l10n_ar_perceptions_basic-8.0.1.0.0.99.dev6-nspkg.pth
odoo_addons/l10n_ar_perceptions_basic/.gitignore
odoo_addons/l10n_ar_perceptions_basic/__init__.py
odoo_addons/l10n_ar_perceptions_basic/__openerp__.py
odoo_addons/l10n_ar_perceptions_basic/account_invoice_view.xml
odoo_addons/l10n_ar_perceptions_basic/invoice.py
odoo_addons/l10n_ar_perceptions_basic/perception.py
odoo_addons/l10n_ar_perceptions_basic/perception_data.xml
odoo_addons/l10n_ar_perceptions_basic/perception_view.xml
odoo_addons/l10n_ar_perceptions_basic/i18n/es.mo
odoo_addons/l10n_ar_perceptions_basic/i18n/es.po
odoo_addons/l10n_ar_perceptions_basic/i18n/es_AR.po
odoo_addons/l10n_ar_perceptions_basic/security/ir.model.access.csv
odoo_addons/l10n_ar_perceptions_basic/static/description/icon.png
odoo8_addon_l10n_ar_perceptions_basic-8.0.1.0.0.99.dev6.dist-info/METADATA
odoo8_addon_l10n_ar_perceptions_basic-8.0.1.0.0.99.dev6.dist-info/WHEEL
odoo8_addon_l10n_ar_perceptions_basic-8.0.1.0.0.99.dev6.dist-info/namespace_packages.txt
odoo8_addon_l10n_ar_perceptions_basic-8.0.1.0.0.99.dev6.dist-info/top_level.txt
odoo8_addon_l10n_ar_perceptions_basic-8.0.1.0.0.99.dev6.dist-info/RECORD
