Metadata-Version: 2.1
Name: odoo8-addon-l10n-ar-perceptions-basic
Version: 8.0.1.0.0.99.dev6
Summary: Perceptions for ARGENTINA (Percepciones) - Basic Module
Home-page: http://e-mips.com.ar
Author: E-MIPS,Odoo Community Association (OCA)
Author-email: support@odoo-community.org
License: GPL-3
Platform: UNKNOWN
Classifier: Programming Language :: Python
Classifier: Framework :: Odoo
Classifier: License :: OSI Approved :: GNU General Public License v3 (GPLv3)
Requires-Python: ~=2.7
Requires-Dist: odoo8-addon-l10n-ar-point-of-sale
Requires-Dist: odoo (<9.0a,>=8.0a)
